ptc_cli/__init__.py
ptc_cli/cli.py
ptc_cli/parser.py
test/__init__.py
ptc_cli-0.0.1.dev20200721153135.dist-info/LICENSE
ptc_cli-0.0.1.dev20200721153135.dist-info/METADATA
ptc_cli-0.0.1.dev20200721153135.dist-info/WHEEL
ptc_cli-0.0.1.dev20200721153135.dist-info/entry_points.txt
ptc_cli-0.0.1.dev20200721153135.dist-info/top_level.txt
ptc_cli-0.0.1.dev20200721153135.dist-info/RECORD
